faaspact_maker/__init__.py
faaspact_maker/definitions.py
faaspact_maker/py.typed
faaspact_maker/types.py
faaspact_maker/build_pact_json/__init__.py
faaspact_maker/build_pact_json/build_pact_json.py
faaspact_maker/build_pact_json/test_build_pact_json.py
faaspact_maker/matchers/__init__.py
faaspact_maker/matchers/definitions.py
faaspact_maker/pact_file_gateway/__init__.py
faaspact_maker/pact_file_gateway/pact_file_gateway.py
faaspact_maker/pact_file_gateway/pact_file_gateway_test.py
faaspact_maker/pact_maker/__init__.py
faaspact_maker/pact_maker/definitions.py
faaspact_maker/pact_maker/pact_maker.py
faaspact_maker/pact_maker/test_pact_maker.py
faaspact_maker/pact_maker/types.py
faaspact_maker-0.0.13.dist-info/LICENSE
faaspact_maker-0.0.13.dist-info/METADATA
faaspact_maker-0.0.13.dist-info/WHEEL
faaspact_maker-0.0.13.dist-info/top_level.txt
faaspact_maker-0.0.13.dist-info/RECORD
